py4track/__init__.py
py4track/__main__.py
py4track/fib.py
py4track-1.2.1a0.data/data/py4track/data.txt
py4track-1.2.1a0.dist-info/METADATA
py4track-1.2.1a0.dist-info/WHEEL
py4track-1.2.1a0.dist-info/top_level.txt
py4track-1.2.1a0.dist-info/zip-safe
py4track-1.2.1a0.dist-info/RECORD
