Metadata-Version: 2.1
Name: py4track
Version: 1.2.1a0
Summary: Python for Track
Home-page: http://github.com/py4track
Author: Helvecio Neto
Author-email: helvecio.neto@inpe.br
License: GPL
Keywords: track
Platform: UNKNOWN
Classifier: Development Status :: 4 - Beta
Classifier: Environment :: Console
Classifier: License :: OSI Approved :: GNU General Public License v3 or later (GPLv3+)
Classifier: Programming Language :: Python :: 3.8
Classifier: Intended Audience :: Developers
Classifier: Operating System :: OS Independent
Classifier: Programming Language :: Python :: Implementation :: CPython
Classifier: Programming Language :: Python :: Implementation :: PyPy
Classifier: Topic :: Utilities
Requires-Dist: cythonize
